{
    "@context": "https://schema.org/",
    "id": "https://lobid.org/project/orca",
    "url": "https://orca.nrw",
    "type": [
        "Project"
    ],
    "name": {
        "de": "Open Resources Campus NRW",
        "en": "Open Resources Campus NRW"
    },
    "alternateName": [
        "ORCA.nrw"
    ],
    "image": "https://www.orca.nrw/sites/default/files/2021-08/orca_logo_claim_rgb.png",
    "description": {
        "de": "ORCA ist ein kostenfreies Online-Portal rund um digital gestütztes Lehren und Lernen an Hochschulen. Die Gruppe Offene Infrastruktur ist  im Rahmen von ORCA.nrw für die zwei Aufgabenbereiche ORCA-Metadateninfrastruktur und ORCA-Suche mit OERSI zuständig."
    },
    "startDate": "2021-02-15",
    "isBasedOn": [
        {
            "id": "https://lobid.org/product/oersi"
        },
        {
            "id": "https://lobid.org/project/amb"
        }
    ],
    "membership": [
        {
            "type": "Role",
            "roleName": {
                "de": "Projektleitung",
                "en": "project lead"
            },
            "member": {
                "id": "http://lobid.org/team/ap#!"
            }
        },
        {
            "type": "Role",
            "roleName": {
                "de": "Datentransformation",
                "en": "data transformation"
            },
            "member": {
                "id": "http://lobid.org/team/tb#!"
            }
        }
    ]
}